examples/__init__.py
examples/multiple.py
examples/simple.py
heartbeats/__init__.py
heartbeats/checker.py
heartbeats/containers.py
heartbeats-0.0.1.dist-info/LICENSE
heartbeats-0.0.1.dist-info/METADATA
heartbeats-0.0.1.dist-info/WHEEL
heartbeats-0.0.1.dist-info/top_level.txt
heartbeats-0.0.1.dist-info/RECORD
