Metadata-Version: 2.1
Name: heartbeats
Version: 0.0.1
Summary: Check heartbeats by method called.
Home-page: https://github.com/zhyipeng/heartbeats
Author: zhyipeng
Author-email: zhyipeng@outlook.com
License: UNKNOWN
Platform: UNKNOWN
Classifier: Programming Language :: Python :: 3
Classifier: License :: OSI Approved :: MIT License
Classifier: Operating System :: OS Independent
Requires-Python: >=3.6
